{
  "project_info": {
    "project_number": "43506521486",
    "project_id": "quizapp1-a364f",
    "storage_bucket": "quizapp1-a364f.appspot.com"
  },
  "client": [
    {
      "client_info": {
        "mobilesdk_app_id": "1:43506521486:android:24fbe40d702ea7f52180df",
        "android_client_info": {
          "package_name": "com.example.quizapp1"
        }
      },
      "oauth_client": [
        {
          "client_id": "43506521486-4v5rr3ohfcdurm75p4t94pshmhqo3hfi.apps.googleusercontent.com",
          "client_type": 3
        }
      ],
      "api_key": [
        {
          "current_key": "AIzaSyDuVlsHVO_mZi7tSF7-jkHzt30EvuUI2ks"
        }
      ],
      "services": {
        "appinvite_service": {
          "other_platform_oauth_client": [
            {
              "client_id": "43506521486-4v5rr3ohfcdurm75p4t94pshmhqo3hfi.apps.googleusercontent.com",
              "client_type": 3
            },
            {
              "client_id": "43506521486-eisiuhs8p5dsvtsbvtunb2ea361730ai.apps.googleusercontent.com",
              "client_type": 2,
              "ios_info": {
                "bundle_id": "com.example.quizapp1"
              }
            }
          ]
        }
      }
    }
  ],
  "configuration_version": "1"
}